{
  "page": 1,
  "image": "images/page_01.jpg",
  "width": 2041,
  "height": 2721,
  "processed_at": "2026-03-06T18:03:07.126493+00:00",
  "pipeline": {
    "layout_model": "PP-DocLayout_plus-L",
    "ocr_model": "mlx-community/GLM-OCR-bf16",
    "ocr_timeout": 25,
    "cleanup_reprocess": true
  },
  "layout": {
    "raw_detections": 144,
    "after_merge": 84
  },
  "regions": [
    {
      "bbox": [
        30,
        253,
        1994,
        376
      ],
      "label": "doc_title",
      "text": "Hundreds Affected When Banks Crash;",
      "status": "ok"
    },
    {
      "bbox": [
        138,
        107,
        286,
        180
      ],
      "label": "text",
      "text": "A MERRY CHRISTMAS",
      "status": "ok"
    },
    {
      "bbox": [
        36,
        218,
        200,
        246
      ],
      "label": "text",
      "text": "30th YEAR No. 17",
      "status": "ok"
    },
    {
      "bbox": [
        26,
        403,
        253,
        565
      ],
      "label": "doc_title",
      "text": "WILSON NAMED RECEIVER FOR LOCAL FIRMS",
      "status": "ok"
    },
    {
      "bbox": [
        28,
        591,
        253,
        690
      ],
      "label": "text",
      "text": "Liabilities Of Taylor And Jenkins, Bankers, May Reach Huge Total Of $80,000",
      "status": "ok"
    },
    {
      "bbox": [
        62,
        708,
        205,
        740
      ],
      "label": "paragraph_title",
      "text": "BROWN LOCATED",
      "status": "ok"
    },
    {
      "bbox": [
        18,
        763,
        257,
        1359
      ],
      "label": "text",
      "text": "Missing Head Of Brown\nAnd Wingate Says He\nWill Return Today.\n\nUpon petition filed by Sharp\nStreet Church through Hawkins\nand McMechen, attorneys, Tuesday.\nTaylor and Jenkins, bankers,\n223 Biddle street, were declared\nbanking by Judge Rose in the U. S.\nDistrict Court. The church had\non deposit $2,623.19. Harry O.\nWilson, well known banker, was\ngranted receiver.\n\nThe bank suspended last Thursday\nannouncing a re-opening Tuesday.\nSeveral hundred persons colled\nearly Tuesday morning, blocking the street, but the doors\nwere not opened. Liabilities of the\nbank it is said, include about $28,000\nin savings deposits, $19,000 in\ncommercial deposits, $22,000 in unpaid Christmas Services Good, and\nmay reach a total of $80,000. A\naccount is due to vary between $50,000 and $75,000.\n\n\"We figured on one third of our Christmas\u5b58\u6b3e to depositing their funds.\" E. P. Taylor, head of the first, a representative of the APO, yesterday. \"Instead most of the $50,000 paid out in Christmas books was held by depositors for their use. Also we were interested for the run on the bank that followed the failure of Brown and Wingate bank, and reduced our cash on hand to less than $500.",
      "status": "ok"
    },
    {
      "bbox": [
        23,
        1361,
        251,
        1531
      ],
      "label": "text",
      "text": "\"You can say for me that our creators will not lose a penny. Our bank is a corporation, and my personal property is not subject to seizure. Nevertheless, I pledge all my posses in making good what the firm owes.\"\n\nA number of depositors were hard hit in the bank's closing, including First Baptist Church, who had on deposit about $15,000. Afro-American Company, $5,000.",
      "status": "ok"
    },
    {
      "bbox": [
        34,
        1537,
        235,
        1573
      ],
      "label": "paragraph_title",
      "text": "Bauker Brown Coming Back",
      "status": "ok"
    },
    {
      "bbox": [
        19,
        1577,
        254,
        2151
      ],
      "label": "text",
      "text": "Judge Rose also appointed Harry O. Wilson receiver for the bank of Brown and Wingate, 1512 Pennsylvania avenue, which closed early last week following the mysterious disappearance of T. Thomas Brown, said to be in Denver, Colorado barring his father-in-law.\n\nMr. Brown called up Mr. Abraham Neal. Park avenue and Presidents square. Monday, saving that he was quarantined in Danville, Va., on account of smallpox, and would return to Baltimore Thursday or Friday.\n\nAnnouncement of the original receivers Archie Hallaway and\u4e39\u59ae Cohen, white, that this bank would pay off Saturday proved a \"false alarm\" to more than three hundred persons, who blocked traffic in front of the bank in the afternoon, open the doors, and take the life of Mr. Brown, who they said skipped town with more than $10,000 in Christmas funds as well as several thousands more of the bank's deposits. They say his return is unlikely, as so far no warrant has been issued for his arrest.\n\nHarry O. Wilson was optimistic when seen by a representative of the APCO. He had not had chance to look over the books of the two banks, but estimated that they had a deficit of $3,000 and the cash balance and juniper, $17,000 in the bank of Tulare and Jenkins, \"it may be several months,\" he added, \"before the affairs of these two banks are wound up.\"",
      "status": "ok"
    },
    {
      "bbox": [
        18,
        2151,
        259,
        2682
      ],
      "label": "text",
      "text": "Asked what effect the return of Mr. Brown would have upon the case, Mr. Wilson said, if Brown returned with money ready to pay off his depositors and make his bank solvent, the matter could easily be turned back into his hands.\n\nBrown and Wingate are said to own the following pieces of property: 1117 Carey street, 1514 Oakland, 1500 Pennsylvania, avenue, 400 Gold street, 1103 and 117 Bolton street, and 625 Lafayette avenue. The heaviest depositors are said to be P. A. Agnew, not $2,500, and M. Boze. $400. Any number of smaller depositors hold \"checks for $10 to $200 in the Christmas Savings Fund.\n\nSurvival of the Fittest\n\n\"The failure of two local colored banks follows in the wake of the failure of a white bank in Baltimore, another on the Eastern Shore and another in Cumberland, Md.\" Mr. Wm. Lewis, of the firm Hutchett and Lewis, bankers, told an APRO representative yesterday.\n\n\"Only the fittest can survive and our institutions do weather the financial storm that thereby gain all the more confidence of people.\"\n\nChristmas checks are being paid by the three remaining colored banks as fast as they are presented, and the banking heads declare themselves prepared to meet any demands made upon them.",
      "status": "ok"
    },
    {
      "bbox": [
        364,
        57,
        824,
        243
      ],
      "label": "text",
      "text": "THE AFRO\n\nEntered in the Postoffice at Baltimore Md. as Second-class matter under the act of March 2, 1879.",
      "status": "ok"
    },
    {
      "bbox": [
        303,
        401,
        473,
        434
      ],
      "label": "paragraph_title",
      "text": "Virginia Bank Fails",
      "status": "ok"
    },
    {
      "bbox": [
        259,
        446,
        510,
        583
      ],
      "label": "text",
      "text": "Norfolk, Va., Dec. 21.\u2014The Mutual Savings Bank, established 1915, is in the hands of a receiver. Its capital stock is $60,000, with $10,000 surplus. $50,000 in Christmas savings funds remain unpaid. The officers are: Levi Brown, president; J. S. Jones, G. W. Brandon, M. D. Bullock, M. L. Holmes, and A. D. Layman, cashiers.",
      "status": "ok"
    },
    {
      "bbox": [
        262,
        607,
        506,
        770
      ],
      "label": "doc_title",
      "text": "RAPE OF HAITI CONFIRMED BY DOCUMENTS",
      "status": "ok"
    },
    {
      "bbox": [
        266,
        795,
        500,
        893
      ],
      "label": "text",
      "text": "Yesterday's Nation Print Documents From Navy Dispatch Book Submitted Senate Committee",
      "status": "ok"
    },
    {
      "bbox": [
        288,
        910,
        470,
        944
      ],
      "label": "paragraph_title",
      "text": "FORCE THREATENED",
      "status": "ok"
    },
    {
      "bbox": [
        261,
        961,
        504,
        1028
      ],
      "label": "paragraph_title",
      "text": "Natives Told To Accept Treaty Or Hard Rule Of United States Troops",
      "status": "ok"
    },
    {
      "bbox": [
        250,
        1042,
        505,
        1606
      ],
      "label": "text",
      "text": "New York City, Dec. 22\u2014Documents confirming the \"rape of Hili\" by the United States government were made public for the first time yesterday by the New York Nation and show how the bravery of a weaker by a stronger nation. The documents which are taken from the United States navy dispatch book and submitted to the Senate Committee, reveal the rough-house methods used by the marines, Navy and State Departments to get control of Hili's revenues; to force the ratification of a disgraceful treaty and to dissolve the Haliian Congress; to enlist unanimous messages is from the Secretary of Navy, Daniels to Adminal Caperton under date of November 10, 1915 authorizing him to tell the Haliian Congress that they should accept a disgraceful treaty with the United States, \"or the United States would, retain control in Hili until the desired end it will forthcoming be accomplished to complete pacification of Hili, etc.\" President D'Artwainave, writing for the Le Newvelist, a Haitian newspaper published in Port au Prince, under date of November 22, 1913 admits that the United States forced Hili to accept the disgraceful treaty or its alternative, namely, the end of a national government, the disappearance of the Haliian flag and a white militant governor from the United States.",
      "status": "ok"
    },
    {
      "bbox": [
        252,
        1607,
        504,
        1736
      ],
      "label": "text",
      "text": "Other dispatches quoted by the Nation show how petty American officers were intrusted with holding up Haitian funds and payment of the Haitian government officials, and how the Haitian assembly was dissolved because it would not adopt a constitution written and dictated by the United States.",
      "status": "ok"
    },
    {
      "bbox": [
        270,
        1744,
        486,
        1778
      ],
      "label": "paragraph_title",
      "text": "Captain Brown Divorced",
      "status": "ok"
    },
    {
      "bbox": [
        254,
        1781,
        503,
        1877
      ],
      "label": "text",
      "text": "Captain George W. Brown, of the 'screamer Starlight, was granted an absolute divorce from his wife, Mrs. Susie Brown, in Circuit Court. Can't help Brown retains his residence, 2103 Deud Hill avenue.",
      "status": "ok"
    },
    {
      "bbox": [
        258,
        1885,
        508,
        2411
      ],
      "label": "text",
      "text": "SPECIAL\nANNOUNCEMENT\nTO THE\nGENERAL PUBLIC\nNotice is hereby given that\non and after\nJanuary 15, 1922\n\nSALE OF STOCK IN THE\nDOUGLASS AMUSEMENT\nCORPORATION WILL BE\nDISCONTINUED\n\nIf You Want This Stock\nBuy It Now\n\nas none can be purchased\nafter date mentioned.\n\nDOUGLASS AMUSEMENT\nCORPORATION\n1212 PENNA. AVENUE\nBALTO., MD.\n\nI. E. Jackson, Manager\nPh., Md. 3709\nBalto., Md.",
      "status": "ok"
    },
    {
      "bbox": [
        515,
        404,
        762,
        486
      ],
      "label": "doc_title",
      "text": "FOUR LOCAL COPS ARE DISAPPOINTED",
      "status": "ok"
    },
    {
      "bbox": [
        515,
        404,
        762,
        486
      ],
      "label": "paragraph_title",
      "text": "FOUR LOCAL COPS ARE DISAPPOINTED",
      "status": "ok"
    },
    {
      "bbox": [
        515,
        517,
        758,
        602
      ],
      "label": "paragraph_title",
      "text": "About To \"Whack Up\" Reward of 5,000 \"Beans\" When Plucky Woman Interfered",
      "status": "ok"
    },
    {
      "bbox": [
        506,
        615,
        761,
        1072
      ],
      "label": "text",
      "text": "Round Sergeant Parr, Sergeant Case, and Patrolmen Koch and Lowman, all white, of the Northwestern district, were interrupted in their plan to \"whack up\" $5,500 among themselves by Mrs. Sarah Hardy, 72 years old, 1921 Denil Hill Avenue. The patrolmen were aided by Mrs. Woodline in capturing Joseph Thomas wanted in Pittsburgh for the murder of Anna M. Kirber, white, last June. Immediately after the crime Thomas escaped to this city and his decease was made known to the police when he identified a watch pawned by Edward Christian, 2122 Division Street, as one taken from a local residence by Thomas. Learning of the arrest of Mr. Christian and knowing that Thomas was invited Thomas around to his house and turned him over to the police. He put up a desperate fight and would have gotten away except for her. While being tried, on the charge of stealing the watch Thomas was identified as the murderer wanted in Pittsburgh and he, along with a jury and found guilty of first-degree murder. His attorney made a motion for a new trial.",
      "status": "ok"
    },
    {
      "bbox": [
        507,
        1071,
        757,
        1225
      ],
      "label": "text",
      "text": "When it was discovered that the four officers whom Mrs. Woodline called to her house were about to divide up the $5,500 reward for Thomas' capture, without telling her about it, she employed a Pittsburgh lawyer holding up the paying of the reward. The case is expected to come up sometime next month. Mrs. Woodline declared that she refused the offer of $500 to compromise the case.",
      "status": "ok"
    },
    {
      "bbox": [
        514,
        1233,
        754,
        1297
      ],
      "label": "paragraph_title",
      "text": "'COMMON LAW' DIVORCE FREES OFFICER PINKNEY",
      "status": "ok"
    },
    {
      "bbox": [
        514,
        1233,
        754,
        1297
      ],
      "label": "doc_title",
      "text": "'COMMON LAW' DIVORCE FREES OFFICER PINKNEY",
      "status": "ok"
    },
    {
      "bbox": [
        506,
        1314,
        758,
        1598
      ],
      "label": "text",
      "text": "If there can be such a thing as a common law marriage, why not a common law divorce. This is the way Miss Austina Bell, of this city, reasoned in a letter to Sergeant Pinkney work wives here. Miss Bell admitted she should have meant to sue for a divorce and agree that both parties go. their own way. Such a common law arrangement, however, caused sorrow to Sergeant Pinkney, now officer on the Pittsburgh Police force. He was arrested last week, charged with bigamy, having recently married a young woman of the Smokey City. When the court directed this situation the court, he was immediately released. Steps will be made to make his divorce from wife number one legal.",
      "status": "ok"
    },
    {
      "bbox": [
        507,
        1687,
        752,
        1953
      ],
      "label": "text",
      "text": "Washington, D. C., Dec. 22. Permission was refused delegates of the Second Colored Work Democracy Congress to appear before delegates of the Disarmament Conference and make a plea for colored equality. Delegates headed by Monroe Trotter and Rev. M. A. Shaw, E. T. Morris and others, of Boston, were permitted to present a petition asking the abolition of color mal-treatment everywhere in the program for world peace.\n\nVERNON 6016-17\nIs the new telephone number of the AFRO-AMERICAN.\n\nVernon 6016-17",
      "status": "ok"
    },
    {
      "bbox": [
        514,
        2035,
        1005,
        2144
      ],
      "label": "text",
      "text": "Mme. Clara Stanley, Prop.\nWHOLESALE AND RETAIL SUPPLY STATION\nWill positively grow the hair. Personal instructions given in the scientific \"APEX\" art of beauty culture and hairdressing.\nPHONE ORDERS DELIVERED",
      "status": "ok"
    },
    {
      "bbox": [
        519,
        2181,
        997,
        2227
      ],
      "label": "text",
      "text": "CHRISTMAS MONDAY, DECEMBER 26th\nNATINEE 3-7 NIGHT 8-1",
      "status": "ok"
    },
    {
      "bbox": [
        530,
        2454,
        992,
        2504
      ],
      "label": "text",
      "text": "Monday evening, January 9th, Richmond Market Armory Sunday evening, January 22nd, Sharp St. Mem. M. E. Church Dolphin Street at Etting",
      "status": "ok"
    },
    {
      "bbox": [
        556,
        2538,
        957,
        2645
      ],
      "label": "text",
      "text": "JONES and JONES\nSchool of Shorthand and Typewriting\nFor information regarding tuition, classes, etc., address\nJAMES A. JONES, Sharp St. Community House\nEtting and Dolphin Streets",
      "status": "ok"
    },
    {
      "bbox": [
        755,
        245,
        1254,
        1291
      ],
      "label": "text",
      "text": "A MODERN MADONNA\n\nCourtesy The Crisis.\n\nAnd she shall bring forth a son, and thou shalt call his name JESUS; for He shall save His people from their sins.\" \u2014Matt. 1-21.\n\nUN-NAMED PRISONER ACCUSES JAIL AUTHORITIES OF MURDER\n\nOne Of Two Letters Dropped From Window Finally Reached Afro Office. Other Letter Re-",
      "status": "ok"
    },
    {
      "bbox": [
        771,
        408,
        1241,
        1045
      ],
      "label": "text",
      "text": "A MODERN MADONNA",
      "status": "ok"
    },
    {
      "bbox": [
        763,
        1062,
        1246,
        1094
      ],
      "label": "text",
      "text": "And she shall bring forth a son, and thou shalt call his name JESUS'; for He shall save His people from their sins\u2014\"Matt. 1-21",
      "status": "ok"
    },
    {
      "bbox": [
        762,
        1115,
        1245,
        1219
      ],
      "label": "doc_title",
      "text": "UN-NAMED PRISONER ACCUSES JAIL AUTHORITIES OF MURDER",
      "status": "ok"
    },
    {
      "bbox": [
        755,
        1322,
        1254,
        1847
      ],
      "label": "text",
      "text": "The following letter dated December 17th, was dropped from a window of the Maryland Penitentiary by an inmate and reached the AFRO-AMERICAN office by mail. This was the second attempt on the part of prison inmates to write the AFRO concerning the murder of Albert Barber, a colored convict who was killed by a white guard last Tuesday. The first letter was tossed over the Madison street wall of the Penitentiary last Friday. It was picked up by Jennie Russell white, 1003 Brentwood street, who took it back to Colonel Swozey, the warden. The jail board met Tuesday and exorcated Joseph Delaney, the guard who did the shooting, and commanded him for his bravery. The letter reads as follows:\n\nWON'T WORK FOR SEVEN DAYS\nChurch Of God And Saints Of Christ Members Will Celebrate Holy Convocation\n\nNotice has been received by local members of the Church of God and Saints of Christ in this city of the Holy Convocation beginning January 3rd and ending January 10th.\n\nSchool Board May Shift Principals\nTransfer of George B. Murphy, principal of School 112, Carey and School streets, from the old to the new building at Calthoun streets, may cause a shifting around of elementary school principals when the School Board meets on Friday.\n\nThe shifting, it is said, will involve the transfer of one of the older principals to old School 112, and the appointment of a new prin-\n\n(Dropped from the window by an inmate of the Maryland Penitentiary.)\n\"Maryland Penitentiary,\nDec. 17, 1921.\nTo the Editor of the Afro-American.\nDear Sir: It may interest you who was shot and killed by Joseph to know that Allen Barber, the man Delaney, Tuesday night, was liberally murdered, and not that in self-decease as the finding of the coroner's inquest indicates.\n\"As this letter must be smuggled out I must be cautious and brief. I shall, therefore attempt to give the silent features of the case which substantiate my accusation. They are as follows:\n\"First. The Prison officials have Continued on page 5.\"",
      "status": "ok"
    },
    {
      "bbox": [
        755,
        1979,
        1254,
        2079
      ],
      "label": "text",
      "text": "APEX GLOSSATINA LATH-O Stanley, Prop. TAIL SUPPLY STATION NEW YEARS MON Maturee and Night DREXEL FREE O Purvia",
      "status": "ok"
    },
    {
      "bbox": [
        755,
        2114,
        1254,
        2397
      ],
      "label": "text",
      "text": "BAY, DECEMBER 26th\nNIGHT 8-1\nY'S HALL\norealis Extravaganza\nE'S CLASSES\nUpsher Songster\nATES FOR CONCERTS OF\nBand, Local No. 543\n8th, Centennial M. E. Church,\n\nHERE IS THE SIMPLE PLAN\nMembers commencing\nMembers commencing\nMembers commencing\nMembers commencing\nMembers commencing",
      "status": "ok"
    },
    {
      "bbox": [
        1019,
        1990,
        1475,
        2073
      ],
      "label": "text",
      "text": "NEW YEARS\u2014MONDAY, JANUARY 2nd Matinee and Night, St. Mary's Hall DREXEL FREE CANDY SHOWER Purviance Classes",
      "status": "ok"
    },
    {
      "bbox": [
        1020,
        2133,
        1982,
        2179
      ],
      "label": "text",
      "text": "HERE IS AN EASY AND SURE WAY TO GET OUR CHECK-JOIN OUR",
      "status": "ok"
    },
    {
      "bbox": [
        1055,
        2296,
        1924,
        2378
      ],
      "label": "text",
      "text": "HERE IS THE SIMPLE PLAN\n\nMembers commencing with 1. and increasing 1c. each week for 50 weeks, receive $12.75 with 2% interest\nMembers commencing with 50c. and decreasing 1c. each week for 50 we",
      "status": "ok"
    },
    {
      "bbox": [
        1049,
        2581,
        1965,
        2632
      ],
      "label": "text",
      "text": "BRANCH OFFICES\u20141604 PENNA. AVE., Tuesday and Saturdays 7-9 P. M. WILSON PARK, Mondays from 7-9 P. M. S. W. Cor. Gilmor and Mulberry Sts., Wednesday and Fridays from 5-8 P. M. 112 S. SHARP ST., Saturdays from EAST BALTIMORE BRANCH, 16 34 McElderry St., Mondays and T. hursdays from 7-9 P. M.",
      "status": "ok"
    },
    {
      "bbox": [
        874,
        224,
        1087,
        245
      ],
      "label": "text",
      "text": "FRIDAY, DEC. 23, 1921",
      "status": "ok"
    },
    {
      "bbox": [
        899,
        1291,
        1094,
        1308
      ],
      "label": "text",
      "text": "turned To Warden",
      "status": "ok"
    },
    {
      "bbox": [
        1005,
        1320,
        1248,
        1613
      ],
      "label": "text",
      "text": "(Dropped from the window by an inmate of the Maryland Penitentiary.)\n\n\"Maryland Penitentiary, Dec. 17, 1921.\n\n\"To the Editor of the Afro-American.\n\n\"Dear Sir: It may interest you who was shot and killed by Joseph to know that Allen Barber, the man Deloney. Tuesday night, was deliberately murdered, and not shot in self defense as the finding of the Coroner's inquest indicates.\n\n\"As this letter must be snuggled out I must be careless and give all the silent features of the case which substantiate my accusation. They are as follows:\n\n\"First. The Prison officials have\n\nContinued on page 5.",
      "status": "ok"
    },
    {
      "bbox": [
        1004,
        1700,
        1254,
        1789
      ],
      "label": "text",
      "text": "Transfer of George B. Murphy, principal of School 112, Carey and School streets, from the old to the new building at Californian streets, may cause a shifting of monetary school principals when the new school opens on Friday.",
      "status": "ok"
    },
    {
      "bbox": [
        1006,
        1788,
        1254,
        1903
      ],
      "label": "text",
      "text": "School Potter needs. The sailing it is said, will involve the transfer of one of the older principals to old School 112, and the appointment of a new principal from the ranks of the teachers.\n\nWILL CELEBRATE",
      "status": "ok"
    },
    {
      "bbox": [
        1006,
        1898,
        1249,
        1979
      ],
      "label": "text",
      "text": "50TH ANNIVERSARY\nRev, and Mrs. John A. Holmes\nwill celebrate their fifteet wedding\nuniversity Sunday, December 25\nRev. Holmes now pastor at Whatcoat A. M. E. Church.",
      "status": "ok"
    },
    {
      "bbox": [
        899,
        1969,
        996,
        2022
      ],
      "label": "text",
      "text": "POMADE\nGLOSSATINA\nLATH-O",
      "status": "ok"
    },
    {
      "bbox": [
        1034,
        2079,
        1223,
        2114
      ],
      "label": "text",
      "text": "Rochester's Orchestra Matinee. 2 to 7",
      "status": "ok"
    },
    {
      "bbox": [
        1262,
        2236,
        1764,
        2291
      ],
      "label": "text",
      "text": "We are in no way connected with any other Christmas Club and have no Branches except those listed below WE HAVE NO AGENTS SOLICITING FOR OUR CLUB",
      "status": "ok"
    },
    {
      "bbox": [
        1254,
        403,
        1499,
        487
      ],
      "label": "doc_title",
      "text": "CANNOT LIVE HERE WITH WHITE WIFE",
      "status": "ok"
    },
    {
      "bbox": [
        1254,
        403,
        1499,
        487
      ],
      "label": "paragraph_title",
      "text": "CANNOT LIVE HERE WITH WHITE WIFE",
      "status": "ok"
    },
    {
      "bbox": [
        1250,
        504,
        1501,
        1002
      ],
      "label": "text",
      "text": "Paul C. Peters Safe As Long As He Stays In Washington, D.C.\n\nMr. and Mrs. Peters, of 50 Myrtle treet, N. W., Washington, are safe from arrest as long as they do not cross the line into Maryland.\n\nMrs. Peters is white and Mr. Peters is colored. They were recently married and are sold together. When their identity was discovered, extradition papers were issued by Governor Ritchie demanding the return and trial of Peters for his violation of the State law for forbidding intermarriage of the races.\n\nPeters was arrested but immediately secured his liberty by furnishing bail. Chief Justice McCoy of the Washington Supreme Court, ruled that Governor Ritchie's papers did not furnish sufficient evidence to show that Peters had been guilty. There is a law in Washington, D.C., to prevent white and colored people marrying and living together. Inquiring at the Marshall's office by a representative of the AFRO-AMERICAN solicited the information that the State will take no further steps against Peters and his white wife as long as they remain in Washington.",
      "status": "ok"
    },
    {
      "bbox": [
        1256,
        1018,
        1497,
        1078
      ],
      "label": "paragraph_title",
      "text": "TWO QUALIFY FOR CITY APPOINTMENTS",
      "status": "ok"
    },
    {
      "bbox": [
        1251,
        1085,
        1496,
        1264
      ],
      "label": "text",
      "text": "Dr. Jesse Wilkens, dentist, corner Pennsylvania Avenue and Pressman Street and Dr. A. D. Stone, 1621 Druid Avenue. Amid repeated dentist visits passed the civil service examinations held recently. Twenty-three whites took the examination and the colored dentists were rated among the first ten. The applicants for dental work in the public schools and in the city hospitals.",
      "status": "ok"
    },
    {
      "bbox": [
        1255,
        1272,
        1490,
        1303
      ],
      "label": "paragraph_title",
      "text": "GOVERNOR PAROLES SEVEN",
      "status": "ok"
    },
    {
      "bbox": [
        1250,
        1319,
        1501,
        1873
      ],
      "label": "text",
      "text": "Prisoners In \"Pen\" and \"Cut\" Get New Year's Gift\nFour men and three women were paroled Thursday by Governor Ritchie, from the Maryland Penitentiary and the House of Correction.\nThose pardoned at the House of Correction are Fannie Pitchet, Zennie Riley, serving one year for shop lifting; Sally Johnson, 5 years for murder, Dennis Cooper, Paul Harris, and Joseph Nugent, for other minor offenses.\nArch Bellows, doing 5\u00bd years for larceny, was the only one paroled from Penitentiary. There were 22 whites paroled.\n\nDoctors and Druggists\nthe world over claim\nHERBS OF LIFE\nthe World's Greatest\nTonic\nBring this Ad. and $1.00 to the\nNORTHWESTERN\nPHARMACY\n1200 Penna. Ave.",
      "status": "ok"
    },
    {
      "bbox": [
        1250,
        1873,
        1501,
        2193
      ],
      "label": "text",
      "text": "and get a large $2.00 bottle of Herbs of Life.\nWe offer no substitutes here\nOut-of-town customers send 10c extra for postage\n\nDAY, JANUARY 2nd\nnight, St. Mary's Hall\nCANDY SHOWER\n\u821e\u4f1a Classes\nUpsher Songster\nNight; 8 to 1\n\nHERE IS AN EASY AND SURE WAY",
      "status": "ok"
    },
    {
      "bbox": [
        1689,
        92,
        1997,
        394
      ],
      "label": "text",
      "text": "U. S. WEATHER REPORT\nDecember 19 to 24, inclusive\nNorth and Middle Atlantic States\nGenerally fair weather but, with\na probability of local snows after\nWednesday. Much colder.\n\n-7 Cents in Maryland\u2014 10 Cents elsewhere\n\nCrash;",
      "status": "ok"
    },
    {
      "bbox": [
        1689,
        2118,
        1997,
        2421
      ],
      "label": "text",
      "text": "JOIN OUR\nB OF 1922\nGREAT RUSH\nChristmas\nbelow\nJOB\nEMENT MAKES YOU A MEMBER\nlive $12.75 with 2% interest\nlive $12.75 with 2% interest\nlive $25.50 with 2% interest\nreceive $25.50 with 2% interest\nlive $63.75 with 2% interest\n2% interest\nh 2% interest\nh 2% interest",
      "status": "ok"
    },
    {
      "bbox": [
        1499,
        465,
        1746,
        596
      ],
      "label": "text",
      "text": "New York City, Dec. 22\u2014Harding did not write his Birmingham speech according to Chandler Owen, writing in the current issue of the Messenger Magazine. He said the sentences are short, direct, reasonably clear and polished and style not Harding: It is probably the work of Hoover, Davis or Week.",
      "status": "ok"
    },
    {
      "bbox": [
        1506,
        621,
        1742,
        781
      ],
      "label": "doc_title",
      "text": "TWELVE YANKS TEN COLORED HANGED ABROAD",
      "status": "ok"
    },
    {
      "bbox": [
        1490,
        781,
        1746,
        1352
      ],
      "label": "text",
      "text": "Evidence Of Witnesses Before Senate Committee Upholds Barbarous Charges\n\nSHORT SHRIFT GIVEN\n\nOne Soldier Taken From Work Gang, Tried And Executed Within Hour\n\nStaff Correspondence Washington, D. C., Dec. 22\u2014Twelve American soldiers were hanged at Camp Wilson, Is-Sur-Tille, France, while he and his \"buddies\"\u2014privates in the Twentieth Paraguay\u2014physiologist on George H. Taylor, of 2737 South Beulah street, Philadelphia, testified today before the Senate committee investigating the charges of Senator \"Tom\" Watson (Dem.) of Georgia that American soldiers were illegally executed and apparently trapped overseen during the World War.\n\n\"On April 25, 1919, I saw three men hung in one day, 'Taylor testified. He said he had offered Watson a photograph of the hangings.\n\n\"I got it from a French sergeant,\" Taylor said. \"I saw the best man, a negro sergeant, hanging from the rope after the execution.\"",
      "status": "ok"
    },
    {
      "bbox": [
        1496,
        1352,
        1744,
        1497
      ],
      "label": "text",
      "text": "\"Now tell us more about the hangings,\" Senator Brandagee said.\n\n\"A white Sergeant named Blodgett,\" Taylor continued \"was hung once and murder after protesting he had not had a chance to be tried.\"\n\n\"After the hanging of Blodgett I saw a major of the medical corps cut out his brains and his heart.\"",
      "status": "ok"
    },
    {
      "bbox": [
        1493,
        1495,
        1740,
        1636
      ],
      "label": "text",
      "text": "\"Did you see any other hungings?\" Senator Shields, (Dem.) or Tennessee asked. \"Yes sir, that same afternoon I saw him engaged for killing a white mess sergeant. \"And who was the next man?\" asked Shields. \"He was a white private who was hung back of the hospital upon the hill.\"",
      "status": "ok"
    },
    {
      "bbox": [
        1494,
        1630,
        1738,
        1658
      ],
      "label": "text",
      "text": "\"How many in all did you see executed,\" persisted Shields,",
      "status": "ok"
    },
    {
      "bbox": [
        1490,
        1713,
        1744,
        1892
      ],
      "label": "text",
      "text": "\"When was the last of these executions?\"\n\"We left us-Sur-Tille June 28, 1919. That we gave before that, but the gallows was there ready to hang more. Three colored fellows were hung a week before we left.\"\nGeorge H. Taylor, 2737 S. Beulah Street, Philadelphia, testified that he saw two soldiers, one colored and one uncolored, in Sur-Tille France, April 1919 and others strung up in uniform later.",
      "status": "ok"
    },
    {
      "bbox": [
        1528,
        1916,
        1713,
        1946
      ],
      "label": "paragraph_title",
      "text": "GET OVER WASHTUBS",
      "status": "ok"
    },
    {
      "bbox": [
        1497,
        1957,
        1745,
        2046
      ],
      "label": "text",
      "text": "Atlanta, Ga., Dec. 22. \u2014Negroes were singled out in a Ku Klux Klan warning issued last week, one of which said: \"Law-abiding, working and protectable Negroes have nothing to pour from us.\"",
      "status": "ok"
    },
    {
      "bbox": [
        1490,
        2045,
        1746,
        2372
      ],
      "label": "text",
      "text": "A second read: \"Nigger women, get in the kitchen and over the wash tubs.\" The third said: \"Nigger men, get in the fields and shop. No loafing allowed anywhere.\"\n\nWAY TO GET OUR CHECK\u2014JOIN OUR LIVING CLUB OR CLUB JOIN BEFORE THE GREATEST days with any other Christmas unless those listed below POLICITING FOR OUR CLUB YOUR FIRST PAYMENT each week for 50 weeks, receive $12.00 each week for 50 weeks, receive $12.00 each week for 50 weeks, receive $25.50 each week for 50 weeks, receive",
      "status": "ok"
    },
    {
      "bbox": [
        1747,
        394,
        1995,
        555
      ],
      "label": "doc_title",
      "text": "VOTE ON ANTI-LYNGHING BILL AFTER HOLIDAYS",
      "status": "ok"
    },
    {
      "bbox": [
        1754,
        574,
        1990,
        684
      ],
      "label": "text",
      "text": "House Postpones Consideration After Democrats Leave Chamber, Making Numerous Roll Call Necessary",
      "status": "ok"
    },
    {
      "bbox": [
        1775,
        695,
        1959,
        728
      ],
      "label": "paragraph_title",
      "text": "MARYLANDERS SPLIT",
      "status": "ok"
    },
    {
      "bbox": [
        1744,
        743,
        1990,
        1255
      ],
      "label": "text",
      "text": "Hill, Zilhman and Mudd\nVotes For; Linthicum,\nBlankeney and Goldsborough Against\n\nStaff Correspondence\nWashington, D. C. Dec. 21\u2014With\nthe Southern members in the\nHouse of Representatives sitting\nwith the governor and the cracker\npress from the Mason and\nDixon's line down to Key West,\nFlorida, howling like wolves, the\nHouse of Representatives moved\nyesterday to postpone the vote of\nthe Dyer Anti Lynching Bill un-\nafter the Christmas Holidays.\nMotion was brought to the House\non Monday by Representative\nCampbell, of Kansas,\nasked the House to limit its deli-\ntion ten days. The debate on the\nmotion occupied the House the\ngreater part of its session Monday\nand was only disposed of after a\ncompromise Tuesday on which\nDemocratic leaders determined to pass the\nbill. Democratic members left\nthe House so that no quorum was\npresent and five roll calls were\nnecessary Monday night.\n\nSergeant-at-arms were sent after arre-\nrors Democrats with threats of\narrest before they could be be-\nhurt knock into the House. Few\nof the Republicans joined the fill-\nhuster.",
      "status": "ok"
    },
    {
      "bbox": [
        1740,
        1255,
        1992,
        1731
      ],
      "label": "text",
      "text": "In an effort to adjourn the House, Monday night and so keep down a discussion of the bill, Congressmen Goldborough and Linthecum, Democrats and Blakeney, Republican were among the representatives who would not join John Philip Hill. Frederick Zihlim and Sydney Mudd, all Republicans voted against adjournment so that the discussion could be continued. Mr. Campbell called attention to the fact that 3,224 persons have been lynched since 1883, and of these 3,522 were colored, including fifty women. The South should not object to the bill, said \"because it will be just as applicable to Ohio as to the South.\" \"Twelve million patriotic, lawabiding colored Americans and more millions of whites are fervently hoping and praying today that Congress and the United States will enact legislation that will forever wipe the stain of lynching on the hide of lynching declared Representative Anselse of New York amid thunders of applause from the Republican side of the House. Representative Garrett, of Tennessee, intimated that lynched was necessary in his section to protect women who travel alone in dark places.",
      "status": "ok"
    },
    {
      "bbox": [
        1747,
        1746,
        1992,
        1795
      ],
      "label": "paragraph_title",
      "text": "Worth Millions; Takes In Washing",
      "status": "ok"
    },
    {
      "bbox": [
        1746,
        1813,
        1997,
        1970
      ],
      "label": "text",
      "text": "Washington, D. C., Dec. 22\u2014A. C. Cooper, a white travelling man herd, told a newspaper reporter that a colored washerwoman in his town continues to take in washing although she is worth $3,000,000 in oil lands. Cooper says she continues her work because possession of a fortune only brought her fear of bodily harm, being poisoned or otherwise murdered.",
      "status": "ok"
    },
    {
      "bbox": [
        1758,
        2007,
        1982,
        2118
      ],
      "label": "text",
      "text": "Is the new telephone number of the AFRO-AMERICAN. The change went into effect this week. The number will be found in the new directory, but it is better to remember Vernon 6016-17",
      "status": "ok"
    }
  ]
}